nive_userdb/__init__.py
nive_userdb/app.py
nive_userdb/i18n.py
nive_userdb/root.py
nive_userdb/user.py
nive_userdb/extensions/__init__.py
nive_userdb/extensions/sessionuser.py
nive_userdb/extensions/tests/__init__.py
nive_userdb/extensions/tests/test_sessionuser.py
nive_userdb/locale/nive_userdb.pot
nive_userdb/locale/de/LC_MESSAGES/nive_userdb.mo
nive_userdb/locale/de/LC_MESSAGES/nive_userdb.po
nive_userdb/locale/fr/LC_MESSAGES/nive_userdb.mo
nive_userdb/locale/fr/LC_MESSAGES/nive_userdb.po
nive_userdb/tests/__init__.py
nive_userdb/tests/__local.py
nive_userdb/tests/db_app.py
nive_userdb/tests/test_app.py
nive_userdb/tests/test_configuration.py
nive_userdb/useradmin/__init__.py
nive_userdb/useradmin/add.pt
nive_userdb/useradmin/adminroot.py
nive_userdb/useradmin/delete.pt
nive_userdb/useradmin/edit.pt
nive_userdb/useradmin/root.pt
nive_userdb/useradmin/view.py
nive_userdb/useradmin/tests/__init__.py
nive_userdb/useradmin/tests/test_configuration.py
nive_userdb/useradmin/tests/test_views.py
nive_userdb/userview/__init__.py
nive_userdb/userview/form.pt
nive_userdb/userview/loginpage.pt
nive_userdb/userview/main.pt
nive_userdb/userview/remove.pt
nive_userdb/userview/signup.pt
nive_userdb/userview/update.pt
nive_userdb/userview/view.py
nive_userdb/userview/mails/contact.pt
nive_userdb/userview/mails/mailpass.pt
nive_userdb/userview/mails/notify.pt
nive_userdb/userview/mails/resetpass.pt
nive_userdb/userview/mails/signup.pt
nive_userdb/userview/mails/verifymail.pt
nive_userdb/userview/static/logo.png
nive_userdb/userview/static/logocms2.png
nive_userdb/userview/tests/__init__.py
nive_userdb/userview/tests/test_configuration.py
nive_userdb/userview/tests/test_views.py
nive_userdb-1.6.2.dist-info/METADATA
nive_userdb-1.6.2.dist-info/WHEEL
nive_userdb-1.6.2.dist-info/top_level.txt
nive_userdb-1.6.2.dist-info/RECORD
